{
  "issues": {
    "issues": [
      {
        "code": "EVENT_ONSET_ORDER",
        "location": "/sub-MSC09/ses-func07/func/sub-MSC09_ses-func07_task-glasslexical_run-02_events.tsv",
        "rule": "rules.checks.events.SortedOnsets",
        "severity": "warning"
      },
      {
        "code": "SIDECAR_KEY_RECOMMENDED",
        "subCode": "StimulusPresentation",
        "location": "/sub-MSC09/ses-func07/func/sub-MSC09_ses-func07_task-glasslexical_run-02_events.tsv",
        "severity": "warning",
        "rule": "rules.sidecars.events.StimulusPresentation",
        "issueMessage": "Field description: Object containing key-value pairs related to the software used to present\nthe stimuli during the experiment.\n"
      },
      {
        "code": "TSV_ADDITIONAL_COLUMNS_UNDEFINED",
        "location": "/sub-MSC09/ses-func07/func/sub-MSC09_ses-func07_task-glasslexical_run-02_events.tsv",
        "rule": "rules.tabular_data.events.Events",
        "subCode": "correct",
        "severity": "warning"
      }
    ]
  }
}