{
  "issues": {
    "issues": [
      {
        "code": "TSV_COLUMN_TYPE_REDEFINED",
        "issueMessage": "Unit \"second\" must be \"s\"",
        "subCode": "onset",
        "location": "/sub-002/ses-01/eeg/sub-002_ses-01_task-gonogo_run-3_events.json",
        "rule": "rules.tabular_data.events.Events",
        "severity": "warning"
      },
      {
        "code": "TSV_COLUMN_TYPE_REDEFINED",
        "issueMessage": "Unit \"millisecond\" must be \"s\"",
        "subCode": "response_time",
        "location": "/sub-002/ses-01/eeg/sub-002_ses-01_task-gonogo_run-3_events.json",
        "rule": "rules.tabular_data.events.Events",
        "severity": "warning"
      }
    ]
  }
}