{
  "issues": {
    "issues": [
      {
        "code": "TSV_COLUMN_TYPE_REDEFINED",
        "issueMessage": "Unit \"seconds\" must be \"s\"",
        "subCode": "onset",
        "location": "/sub-03/ses-01/func/sub-03_ses-01_task-compLn_run-2_events.json",
        "rule": "rules.tabular_data.events.Events",
        "severity": "warning"
      },
      {
        "code": "TSV_COLUMN_TYPE_REDEFINED",
        "issueMessage": "Unit \"seconds\" must be \"s\"",
        "subCode": "duration",
        "location": "/sub-03/ses-01/func/sub-03_ses-01_task-compLn_run-2_events.json",
        "rule": "rules.tabular_data.events.Events",
        "severity": "warning"
      }
    ]
  }
}